TANWEE/__init__.py
TANWEE/setup.py
TANWEE-0.1.dist-info/LICENSE.txt
TANWEE-0.1.dist-info/METADATA
TANWEE-0.1.dist-info/WHEEL
TANWEE-0.1.dist-info/top_level.txt
TANWEE-0.1.dist-info/RECORD
