Metadata-Version: 2.1
Name: TANWEE
Version: 0.1
Summary: A test library for demonstrating Python packaging
Author: TAN
Classifier: Programming Language :: Python :: 3
Classifier: Operating System :: OS Independent
Classifier: License :: OSI Approved :: MIT License
Requires-Python: >=3.6
License-File: LICENSE.txt
